[
    {
        "name": "Base Resources Package [Latest]",
        "pkg": "https://drive.google.com/uc?export=download&id=1vf9Mb5VVwrOcTs6j4l0WWBq3JnO8GUTk"
    },
    {
        "name": "Nighly Alpha for Debug Only",
        "pkg": "https://www.mediafire.com/file/0ctvwchlnpg46zb/Build.zip/file"
    },
    {
        "name": "Open Beta Pre 1.0 [Latest]",
        "hfw": "",
        "dfw": "",
    },
    {
        "name": "Previous 1.0 fix 3",
        "hfw": "...",
        "dfw": "..."
    },
    {
        "name": "prebeta 0.1b3"
    },
    {
        "name": "prebeta 0.1b3"
    },
    {
        "name": "prebeta 0.1b2"
    },
    {
        "name": "prebeta 0.1"
    },
    {
        "name": "developer 0"
    }
]
